ronkyuu/__init__.py
ronkyuu/relme.py
ronkyuu/tools.py
ronkyuu/validators.py
ronkyuu/webmention.py
ronkyuu-0.9.dist-info/LICENSE
ronkyuu-0.9.dist-info/METADATA
ronkyuu-0.9.dist-info/WHEEL
ronkyuu-0.9.dist-info/top_level.txt
ronkyuu-0.9.dist-info/RECORD
