Metadata-Version: 2.1
Name: ronkyuu
Version: 0.9
Summary: "Webmention Manager"
Home-page: https://github.com/bear/ronkyuu
Author: Mike Taylor and Kartik Prabhu
Author-email: bear@bear.im
License: CC0 1.0 Universal
Platform: UNKNOWN
Classifier: Programming Language :: Python :: 3
Classifier: License :: OSI Approved :: MIT License
Classifier: Operating System :: OS Independent
Classifier: Topic :: Software Development :: Libraries :: Python Modules
Requires-Python: >=3.9
